README.md
setup.py
ep_sdk_4pd/__init__.py
ep_sdk_4pd/ep_data.py
ep_sdk_4pd/ep_system.py
ep_sdk_4pd/models.py
ep_sdk_4pd.egg-info/PKG-INFO
ep_sdk_4pd.egg-info/SOURCES.txt
ep_sdk_4pd.egg-info/dependency_links.txt
ep_sdk_4pd.egg-info/requires.txt
ep_sdk_4pd.egg-info/top_level.txt
tests/test.py
tests/test_2.py
tests/test_call_train_done.py
tests/test_get_run_strategy.py
tests/test_get_system_date.py
tests/test_history_data.py
tests/test_model1.py
tests/test_model_output_dir.py
tests/test_predict_data.py