Metadata-Version: 2.1
Name: ep_sdk_4pd
Version: 6.0.4
Summary: 4paradigm Electricity Platform Service SDK Library for Python
Home-page: https://gitlab.4pd.io/electricityproject/electricity-platform-sdk
Author: 4paradigm Electricity Platform SDK
Author-email: 
Keywords: 4pd_electricity_platform
Platform: any
Classifier: Intended Audience :: Developers
Classifier: Programming Language :: Python
Classifier: Programming Language :: Python :: 3
Classifier: Programming Language :: Python :: 3.6
Classifier: Programming Language :: Python :: 3.7
Classifier: Programming Language :: Python :: 3.8
Classifier: Programming Language :: Python :: 3.9
Classifier: Programming Language :: Python :: 3.10
Classifier: Topic :: Software Development
Requires-Python: >=3.6
Requires-Dist: requests
